jumpstarter_driver_corellium/__init__.py
jumpstarter_driver_corellium/client.py
jumpstarter_driver_corellium/driver.py
jumpstarter_driver_corellium/driver_test.py
jumpstarter_driver_corellium/corellium/__init__.py
jumpstarter_driver_corellium/corellium/api.py
jumpstarter_driver_corellium/corellium/api_test.py
jumpstarter_driver_corellium/corellium/exceptions.py
jumpstarter_driver_corellium/corellium/types.py
jumpstarter_driver_corellium-0.7.4.dist-info/METADATA
jumpstarter_driver_corellium-0.7.4.dist-info/WHEEL
jumpstarter_driver_corellium-0.7.4.dist-info/entry_points.txt
jumpstarter_driver_corellium-0.7.4.dist-info/RECORD
